tekleo_common_message_protocol/__init__.py
tekleo_common_message_protocol/image_base64.py
tekleo_common_message_protocol/image_url.py
tekleo_common_message_protocol/ping_output.py
tekleo_common_message_protocol/point_pixel.py
tekleo_common_message_protocol/point_relative.py
tekleo_common_message_protocol/rectangle_pixel.py
tekleo_common_message_protocol/rectangle_relative.py
tekleo_common_message_protocol/text.py
tekleo_common_message_protocol/doc/__init__.py
tekleo_common_message_protocol/doc/doc_page.py
tekleo_common_message_protocol/doc/doc_page_sector.py
tekleo_common_message_protocol/facial_features/__init__.py
tekleo_common_message_protocol/facial_features/facial_prediction.py
tekleo_common_message_protocol/nlp/__init__.py
tekleo_common_message_protocol/nlp/nlp_named_entity.py
tekleo_common_message_protocol/object_detection/__init__.py
tekleo_common_message_protocol/object_detection/od_labeled_item.py
tekleo_common_message_protocol/object_detection/od_output.py
tekleo_common_message_protocol/object_detection/od_prediction.py
tekleo_common_message_protocol/object_detection/od_sample.py
tekleo_common_message_protocol-0.0.0.6.dist-info/LICENSE.txt
tekleo_common_message_protocol-0.0.0.6.dist-info/METADATA
tekleo_common_message_protocol-0.0.0.6.dist-info/WHEEL
tekleo_common_message_protocol-0.0.0.6.dist-info/top_level.txt
tekleo_common_message_protocol-0.0.0.6.dist-info/RECORD
