Metadata-Version: 2.1
Name: tekleo-common-message-protocol
Version: 0.0.0.6
Summary: UNKNOWN
Home-page: https://github.com/jpleorx/tekleo-common-message-protocol
Author: Leo Ertuna
Author-email: leo.ertuna@gmail.com
License: Creative Commons Attribution-NonCommercial-NoDerivatives 4.0 International Public License
Download-URL: https://pypi.org/project/tekleo-common-message-protocol/
Platform: UNKNOWN
Requires-Dist: pydantic
Requires-Dist: simplestr
Requires-Dist: Pillow
